friendly_names/__about__.py
friendly_names/__init__.py
friendly_names/adjectives.py
friendly_names/nouns.py
friendly_names/verbs.py
friendly_names-0.1.2.dist-info/METADATA
friendly_names-0.1.2.dist-info/WHEEL
friendly_names-0.1.2.dist-info/licenses/LICENSE.txt
friendly_names-0.1.2.dist-info/RECORD
