Metadata-Version: 2.4
Name: friendly_names
Version: 0.1.2
Summary: Generate friendly, readable names by combining adjectives, nouns and verbs
Project-URL: Documentation, https://github.com/jkassemi/friendly_names#readme
Project-URL: Issues, https://github.com/jkassemi/friendly_names/issues
Project-URL: Source, https://github.com/jkassemi/friendly_names
Author-email: James Kassemi <james@kassemi.org>
License-Expression: MIT
License-File: LICENSE.txt
Keywords: friendly,generator,names,readable
Classifier: Development Status :: 4 - Beta
Classifier: Intended Audience :: Developers
Classifier: Programming Language :: Python
Classifier: Programming Language :: Python :: 3.8
Classifier: Programming Language :: Python :: 3.9
Classifier: Programming Language :: Python :: 3.10
Classifier: Programming Language :: Python :: 3.11
Classifier: Programming Language :: Python :: 3.12
Classifier: Programming Language :: Python :: Implementation :: CPython
Classifier: Programming Language :: Python :: Implementation :: PyPy
Classifier: Topic :: Software Development :: Libraries :: Python Modules
Classifier: Topic :: Text Processing :: General
Classifier: Topic :: Utilities
Requires-Python: >=3.8
